README.md
setup.py
impython/__init__.py
impython/__main__.py
impython/impython.py
impython.egg-info/PKG-INFO
impython.egg-info/SOURCES.txt
impython.egg-info/dependency_links.txt
impython.egg-info/top_level.txt