Metadata-Version: 2.1
Name: impython
Version: 0.1.0
Summary: impython is a python interpreter that accepts pipe stdin inputs and recognizes some magic commands. 
Home-page: https://gitee.com/junruoyu-zheng/impython
Author: junruoyu-zheng
Author-email: zhengjry@outlook.com
License: UNKNOWN
Platform: UNKNOWN
Classifier: Programming Language :: Python :: 3
Classifier: License :: OSI Approved :: MIT License
Classifier: Operating System :: OS Independent
